{
    "Index": {
      "brandName": "ChatFlow AI",
      "nav": {
        "features": "Funkciók",
        "pricing": "Árak",
        "login": "Bejelentkezés"
      },
      "hero": {
        "title": "Építsen Intelligensebb Chatbotokat Messengerre és WhatsAppra",
        "description": "Vonja be ügyfeleit, automatizálja a támogatást és generáljon leadeket intuitív, kód nélküli vizuális chatbot-építőnkkel. MI alapokon.",
        "cta": "Kezdje Ingyen"
      },
      "features": {
        "title": "Minden, Amire az Intelligensebb Beszélgetésekhez Szüksége Van",
        "f1Title": "Vizuális Folyamatépítő",
        "f1Desc": "Tervezzen összetett chatbot-beszélgetéseket egy egyszerű fogd és vidd felülettel. Nincs szükség kódolásra.",
        "f2Title": "MI Tudásügynök",
        "f2Desc": "Tanítsa be chatbotját saját adataival, hogy pontosan és azonnal válaszoljon az ügyfelek kérdéseire.",
        "f3Title": "Többplatformos Támogatás",
        "f3Desc": "Telepítse chatbotjait zökkenőmentesen a Facebook Messengerre és a WhatsAppra is egyetlen platformról."
      },
      "cta": {
        "title": "Készen Áll az Ügyfélkapcsolat Automatizálására?",
        "description": "Regisztráljon még ma, és percek alatt elkezdheti építeni első MI chatbotját.",
        "cta": "Kezdje el az Építést Most"
      },
      "footer": {
        "copyright": "Minden jog fenntartva."
      }
    },
    "Auth": {
      "loginTitle": "Üdvözöljük újra",
      "loginDescription": "Adja meg hitelesítő adatait a vezérlőpulthoz való hozzáféréshez.",
      "registerTitle": "Hozzon létre egy Fiókot",
      "registerDescription": "Kezdje el építeni MI chatbotját percek alatt.",
      "emailLabel": "E-mail",
      "passwordLabel": "Jelszó",
      "loginButton": "Bejelentkezés",
      "registerButton": "Fiók Létrehozása",
      "noAccount": "Nincs még fiókja?",
      "haveAccount": "Már van fiókja?",
      "signUp": "Regisztráció",
      "signIn": "Bejelentkezés"
    },
    "Dashboard": {
      "title": "Vezérlőpult",
      "welcome": "Üdvözöljük a Vezérlőpulton!",
      "welcomeDescription": "Ez a központi felület a chatbotok, kapcsolatok és beállítások kezeléséhez.",
      "logout": "Kijelentkezés",
      "navDashboard": "Vezérlőpult",
      "navConnections": "Kapcsolatok",
      "navSettings": "Beállítások",
      "brandName": "ChatFlow AI"
    },
    "Connections": {
      "title": "Kapcsolatok Kezelése",
      "description": "Csatlakoztassa közösségi média fiókjait a beszélgetések automatizálásának megkezdéséhez.",
      "connectFacebook": "Facebook Oldal Csatlakoztatása",
      "connectedAccounts": "Csatlakoztatott Fiókok",
      "noAccounts": "Még nem csatlakoztatott egyetlen fiókot sem."
    },
    "Metadata": {
      "title": "MI Chatbot Építő Messengerre és WhatsAppra",
      "description": "Építsen kód nélküli MI chatbotokat a Facebook Messengeren és WhatsAppon folytatott beszélgetések automatizálásához. Vonja be az ügyfeleket, kezelje a támogatást és generáljon leadeket.",
      "keywords": "chatbot, mi, messenger, whatsapp, saas, automatizálás, kód nélkül"
    }
  }